{
  "schema": "zocr-neural-protected/v1",
  "mandate_id": "ZOCR_FIELD_ROBOTICS_MANDATE_v1",
  "network_id": "ZOCR_FIELD_ASSIST_v1",
  "rule": "Protected neural assistance — localhost only, sealed weights, mandate gate",
  "egress": false,
  "layers": [
    {
      "id": "features",
      "in": 16,
      "out": 16,
      "activation": "identity",
      "note": "Image metrics + stereo + preserve features"
    },
    {
      "id": "hidden",
      "in": 16,
      "out": 8,
      "activation": "relu",
      "weights": [
        [0.12, -0.08, 0.22, 0.05, -0.15, 0.18, 0.09, -0.11, 0.14, 0.06, -0.07, 0.19, 0.03, -0.13, 0.16, 0.10],
        [-0.06, 0.17, 0.04, -0.12, 0.21, -0.09, 0.13, 0.08, -0.14, 0.11, 0.07, -0.05, 0.20, -0.10, 0.15, 0.02],
        [0.09, -0.11, 0.16, 0.07, -0.04, 0.18, -0.13, 0.12, 0.05, -0.08, 0.19, 0.14, -0.06, 0.10, -0.15, 0.21],
        [0.15, 0.03, -0.09, 0.20, 0.06, -0.12, 0.11, -0.07, 0.17, 0.04, -0.14, 0.08, 0.13, -0.05, 0.18, -0.10],
        [-0.08, 0.14, 0.10, -0.16, 0.09, 0.05, -0.11, 0.19, -0.07, 0.12, 0.15, -0.04, 0.08, 0.17, -0.13, 0.06],
        [0.11, -0.05, 0.18, -0.09, 0.14, 0.07, -0.16, 0.04, 0.20, -0.12, 0.06, 0.13, -0.08, 0.15, 0.09, -0.11],
        [0.07, 0.19, -0.12, 0.08, -0.06, 0.15, 0.10, -0.14, 0.05, 0.17, -0.09, 0.11, 0.16, -0.04, 0.13, 0.08],
        [-0.13, 0.06, 0.11, 0.15, -0.10, 0.09, 0.17, -0.05, 0.08, -0.16, 0.14, 0.04, -0.07, 0.12, 0.19, -0.08]
      ],
      "bias": [0.02, -0.01, 0.03, 0.0, -0.02, 0.01, 0.02, -0.01]
    },
    {
      "id": "output",
      "in": 8,
      "out": 6,
      "activation": "softmax",
      "labels": ["clear_field", "ui_dense", "motion_hint", "low_light", "threat_pattern", "stereo_depth"],
      "weights": [
        [0.22, -0.10, 0.15, 0.08, -0.12, 0.18, 0.05, -0.07],
        [-0.08, 0.19, 0.06, -0.14, 0.11, 0.04, 0.17, -0.09],
        [0.12, 0.05, -0.11, 0.20, -0.06, 0.14, 0.08, -0.13],
        [0.09, -0.15, 0.18, 0.03, 0.16, -0.08, 0.11, 0.07],
        [-0.11, 0.08, 0.13, -0.07, 0.19, 0.10, -0.14, 0.15],
        [0.14, -0.06, 0.09, 0.17, -0.05, 0.12, 0.16, -0.10]
      ],
      "bias": [0.0, 0.0, 0.0, 0.0, 0.0, 0.0]
    }
  ],
  "assist": {
    "max_tokens": 512,
    "local_only": true,
    "flash_forbidden": true
  }
}